auto_python_toolkit/README.md
auto_python_toolkit/__init__.py
auto_python_toolkit/__main__.py
auto_python_toolkit/cli.py
auto_python_toolkit/dependency_analyzer.py
auto_python_toolkit/i18n.py
auto_python_toolkit/toolkit.py
auto_python_toolkit-0.1.0.dist-info/METADATA
auto_python_toolkit-0.1.0.dist-info/WHEEL
auto_python_toolkit-0.1.0.dist-info/entry_points.txt
auto_python_toolkit-0.1.0.dist-info/licenses/LICENSE
auto_python_toolkit-0.1.0.dist-info/RECORD
