Metadata-Version: 2.4
Name: auto-python-toolkit
Version: 0.1.0
Summary: Create offline-ready Python environments for your projects
Project-URL: Homepage, https://github.com/tkpdx01/auto-python-toolkit
Project-URL: Bug Tracker, https://github.com/tkpdx01/auto-python-toolkit/issues
Project-URL: Documentation, https://github.com/tkpdx01/auto-python-toolkit#readme
Project-URL: Source Code, https://github.com/tkpdx01/auto-python-toolkit
Author-email: tkpdx01 <tkpdx01@outlook.com>
License: MIT
License-File: LICENSE
Keywords: environment,offline,packaging,python,uv
Classifier: Development Status :: 4 - Beta
Classifier: Environment :: Console
Classifier: Intended Audience :: Developers
Classifier: License :: OSI Approved :: MIT License
Classifier: Operating System :: Microsoft :: Windows
Classifier: Programming Language :: Python :: 3
Classifier: Programming Language :: Python :: 3.7
Classifier: Programming Language :: Python :: 3.8
Classifier: Programming Language :: Python :: 3.9
Classifier: Programming Language :: Python :: 3.10
Classifier: Programming Language :: Python :: 3.11
Classifier: Programming Language :: Python :: 3.12
Classifier: Topic :: Software Development
Classifier: Topic :: Utilities
Requires-Python: >=3.7
Requires-Dist: uv>=0.1.10
